{"TyoZdkZadjE6S1AtCN/4Gw==":"fundo-inicial.jpg","wdZS7o3VjQ+BzwbExqj97Q==":"1.jpg","kPsyeOCQRpestiVt91eTeA==":"4dc10885-16a8-4014-9e9f-00b3dbfab9f7.jpg","K6r97RnkNdBU2XeD6PuJPg==":"4dc10885-16a8-4014-9e9f-00b3dbfab9f7.jpeg","dHfsf4Zi9K5+XAIGCYbUIA==":"11aa0c9f-2759-4d15-96b5-c939ba3b83d7.jpg","2rcbXmR1jLcJEstPwD1F1g==":"1.jpeg","vLN3EyWWHcn3kkaJLIjq9g==":"site-temponatureza.png","bjyDJbxRv+Fl5bE5ZIueug==":"significado-de-sonhos-com-natureza.jpg","Jj6y0a/PF0VyyiJwzcLI3g==":"significado-de-sonhos-com-natureza.jpeg","3w7kmEFOlV0GZ3VTW/NhFQ==":"img-2417.jpg","MTQmFqTT4OUjnG0OD9L5Sw==":"img-2417.jpeg","VftODOR4kcbaBHVKaL1FGw==":"diadaarvore.jpg","Gjkjw6Wgld0qh4s0NWSZ1A==":"24ad9317-2e33-41c3-9631-0211e68ca60c.jpg","iZyH8hD03SRDe/KAAIOOkw==":"confira-6-destinos-brasileiros-de-viagem-para-aproveitar-a-natureza-1.jpg","1WOCsBUL6prBlba+NwsLvA==":"591f7b6a-e7b0-4343-850a-95162203cc8d.jpg","A9A7S6tHATw7IntX5Xs4/w==":"e9a62e7e-3a86-4bc5-b7c1-55d58ea2f4c2.jpg","tGaJtSHVOFe+HZKqtlR2fQ==":"f4764bb9-d366-4ac2-b18c-571a6a4a3c67.jpg","gEpjAU00diP9d4UZPJ3R7A==":"download.jpg","RM/pXK/+CcnrhG+mAlg+qw==":"15778185035e0b9987d7bd0-1577818503-3x2-md.jpg","9X7yKV+/y8AWBy2H+f0iUA==":"unnamed.jpg","TfQvzP+Zitcr6WRROQloLA==":"04af33a7-5e11-48f2-a6df-7c7bc8c39a1d.jpg","0FH04G0Ht4dVtSD+P1L94w==":"schlachtplatte.jpg","lpXxpF8DDsdtIKeX116rYQ==":"1662382974.jpg","jzvGiCpdRXWLRBXWDMtlOw==":"3-2.png","hGQk5Ja5faiyRNqdqEGF7Q==":"3-3.png","ZydpmRZzhk0HHghgQZFlfA==":"schlachtplatte.jpeg","Epokao7RdSg2HNLad+ZLHw==":"gallery-fat-tire-tours-munich-oktoberfest-festival-22x.jpg","0RD5ITiItd7mkvIH+L7+BA==":"minifundio.jpg","msanmR3MRYMvJeDclrCwGg==":"saiba-como-harmonizar-o-vinho-com-pratos-tipicos-do-inverno52-1-thumb-570.jpg","C7d2QkPsS1m4ZNrkNnoCyQ==":"caminho-de-pedras-bento-gonalves.jpg","ozT10IMuZyBsWLA3Br37PA==":"residencial11-smart-depois.png","dMYqmLaD+58JgYqg2xO+rQ==":"e31f82e4-3606-4051-b4a6-14009d0d3d96.jpg","iY1nGj7aVwGmXPY6v4c4Wg==":"mercado-de-pinheiros-sao-paulo-3.jpg","bmlClSFTo/eVr5sff+1sWw==":"turismo-rural-carlos-jr.jpg","yR5A62sO6CSIZbLJvrTFhw==":"b6a15bec-32cf-4a70-92eb-e7e084b8317b.jpg","3cqndLXZfEUaxOrBfjFuvA==":"cavalgada-turismo-rural-ecologico-artigos-cursos-cpt.jpg","nFWFxw6xquXQqrOB85YDQQ==":"620a0efc-cbf6-45e9-83f4-9f2533f814c1.jpg","FAthkmdFIBJiMbCPWvM5GQ==":"144519-hotel-fazenda-igarapes.jpg","8Dff3EHyukN1H/gyGoIzsw==":"20170731185625-caminhos-de-pedra-1.jpg","wvPvQSmS0VqqIK8cesZ0ng==":"unnamed-1.jpg","tlOUje3oyzcz0vdXL8hWnA==":"100559-20181010162928850.jpg","+DXexu0QIgScCkZlDG/0TQ==":"100559-20181010162928850.jpeg","qdlYcrdt+sHmYrJbZ+b8Tw==":"1487792083.jpg","wolknI2HgWeMvP4z1GTb8A==":"02.1.jpg","XSN74sZ0zrfDXXzr+y5lzg==":"banco-de-imagens.jpg","/OHUEqvXrctleNvXo2cBew==":"por-do-sol-1080x720.jpg","l5IwEPfzxin0osk5klPFCg==":"656x0.jpg","VKlMfmEZ5vlFEQ21S1z1CA==":"656x0.jpeg","owmOD4IbnHlFcAeqXgLwbQ==":"3f347c68-a0da-4d6f-a80b-d10913064e62.jpg","EeZ5/fcBYBMFOJRVcny8BA==":"5-benefcios-dos-queijos-para-a-sade.jpg","wlUAg+9NQoyFyus1/A1S7A==":"images.jpg","+OmJZDGktY5AUfu7t4V3vA==":"tecnologia-no-campo.jpg","m1ebnT2JkpPOaya3+jA47Q==":"mbr.jpg","JUHOMTjiW7o0c4j8FBcBPA==":"dd.png","n/RdlvtcNI8+WqwAlOKH9w==":"popu.png","+NQq/Eu/L0K9zjGxlvR1Qw==":"dens.png","F8uLsG5Q+lkaQc0fVXxqyw==":"sala.png","5Wzvws69IwNEtY0BshbUSg==":"sala-1.png","3EHZ8G40JNAq7Be1Qp2tBw==":"taxa.png","ey2e3NYL8dB5uipkokkruw==":"pib.png","b8hm6xunf6IScwtbphu4uQ==":"idh.png","9K2Zmh0e9zSB19J2M8NSQQ==":"esta.png","B6K0L+hOAQjA2iyzTfOgPA==":"unidade-terr.png","FbQzU5MVOmoYa/IXjEVE8A==":"esg.png","p9WkjIJaUdsINZNy5zN9rg==":"arb.png","96obZeQzhsEXIbCab/8KuA==":"idms.png","/5TxP6rB5Xsj6wML99MSww==":"logo2.png","eW9VOwy9FzQBCBy7hORpgw==":"img-2418.jpeg","n/OJ1D3Dj71EyKieIvaO5w==":"mapa-sintese.png","Bmz/VS3TJ0XQp4I4nF23SQ==":"mapa-sintese-1.png","tSk2iSUPpAF/lhlX4SH76g==":"dois.png","F+lN8M3MQKZvX5XRv5KYVg==":"dois-1.png","QpARGWuwMDNjqJofejqKsg==":"tres.png","zc6pZFYgsK9lWotlDdw9rw==":"tres-1.png","9+PoyhzxXpYOsPoKj2MrPw==":"tres01.png","mtMreqQMBD/zJe+puRCYHQ==":"mapa-sintese-2.png","KJUfFua0vXQXRlyK84+7bg==":"oi.png","a4+jixKE8dpoEduQ/GZxCw==":"oi-1.png","5UcP7AwJlvfqTQbOUl1YKA==":"oi0.png","tuP7ALcfy6dNU7ZGTA7Hhg==":"mbr-1.jpg","spV3JDQJbryJ5iAy0SYKpA==":"mbr.png","PokQrZE91KroBdfSIIC/zQ==":"mbr-1.png","PMAxlyk1Rv+18l2dWfBvzQ==":"mbr-2.png","IyBR509dHE0z8jjoollloQ==":"mbr-3.png","S+r9xSvxp42OVChcjmojxA==":"mbr-4.png","ZiW3JhFIVfPAg1suBTFv1A==":"mbr-5.png","VxLmiZsckvFn3xJtjuzagQ==":"mbr-6.png","8+pe6xdaTIdBkdj2DxdKCg==":"mbr-2.jpg","GC77RSo+mJD7LtnBBmF5kg==":"mbr-3.jpg","aVkw/6pV2GVYh4yMJBuNRA==":"aviao.jpg","eP87WQvQvXPI4osJs/tfGQ==":"pacote.jpg","nEUAj6nENjmitRFPoPCMww==":"aviao.jpeg","olAq8Ffllly+KpsGDhNe1A==":"aviao-1.jpeg","/sNGVaVvcBd0M+8lOMRWeQ==":"clima.jpg","0MFpkm2fIJGqMRnB2J2pQw==":"clima.jpeg","MNntqdAKYxYojA7kdJ68Ig==":"clima-1.jpeg","/1lCs8+u/dVZRcm1nZfr6g==":"clima-2.jpeg","P4uKhIo3fB+P7Z8Yo672Ug==":"pacote.jpeg","y1u1XiaSTG7z5LxGUq3mUQ==":"estao.jpg","y3I3sd7nfeNqMLp7AxjfOQ==":"mbr-4.jpg","xeobnYpJ5w66EeDUq+mCsA==":"mbr-5.jpg","tXKJ8Ghi2teZlekeeJmm6w==":"mbr-6.jpg","aWj/0mCkKE4Gc9mELkGpCg==":"mbr-7.jpg","qFQ0fslVzsUvxgSbZ/RHLg==":"mbr-8.jpg","Fg2eW3SnqZ+8xjavjnSDFg==":"mbr-9.jpg","O4VpQUc2A0Q1PQInXInE9g==":"mbr-10.jpg","Xr1qce6vpvG9KGc0KgctSQ==":"mbr-11.jpg","kEOXizku4BK0gXnpxiIZyg==":"mbr-12.jpg","hEquHLSLYYqmZWQlH+ILUQ==":"mbr-13.jpg","wrVbfWLkf2oMxQxiH71F8A==":"mbr-14.jpg","o1vx8pnuhrOUpCDHUsNg/A==":"mbr-15.jpg","XH62wI7MX74ykJWG77Rfuw==":"feijoada.jpg"}